iverilog_test/proj.v
module counter (
    input wire reset,
    input wire clk,
    input wire [7:0]wdata,
    input wire wr,
    output reg [7:0]data
);
always @ (posedge clk or posedge reset)
    if (reset)
       data <= 8'h00;
    else
    if(wr)
    begin
       data <= wdata;
       $display("written %h",wdata);
    end
   else
      data <= data + 8'h01;
endmodule

iverilog_test/tproj.v
module test_counter;

reg reset, clk, wr;
reg [7:0]wdata;
wire [7:0] data_cnt;

//устанавливаем экземпляр тестируемого модуля
counter counter_inst(reset, clk, wdata, wr, data_cnt);

//моделируем сигнал тактовой частоты
always
  #5 clk = ~clk;

//от начала времени...

initial
begin
  clk = 0;
  reset = 0;
  wdata = 8'h00;
  wr = 1'b0;

//через временной интервал "50" подаем сигнал сброса
  #50 reset = 1;

//еще через время "4" снимаем сигнал сброса

  #4 reset = 0;

//пауза длительностью "50"
  #50;

//ждем фронта тактовой частоты и сразу после нее подаем сигнал записи
  @(posedge clk)
  #0
    begin
      wdata = 8'h55;
      wr = 1'b1;
    end

//по следующему фронту снимаем сигнал записи
  @(posedge clk)
  #0
    begin
      wdata = 8'h00;
      wr = 1'b0;
    end
end

//заканчиваем симуляцию в момент времени "400"
initial
begin
  #810 $finish;
end

//создаем файл VCD для последующего анализа сигналов
initial
begin
  $dumpfile("out.vcd");
  $dumpvars(0,test_counter);
end

//наблюдаем на некоторыми сигналами системы
initial
$monitor($stime,, reset,, clk,,, wdata,, wr,, data_cnt);

endmodule

iverilog_test/out.vcd
$date
	Tue May 15 17:58:12 2018
$end
$version
	Icarus Verilog
$end
$timescale
	1s
$end
$scope module test_counter $end
$var wire 8 ! data_cnt [7:0] $end
$var reg 1 " clk $end
$var reg 1 # reset $end
$var reg 8 $ wdata [7:0] $end
$var reg 1 % wr $end
$scope module counter_inst $end
$var wire 1 " clk $end
$var wire 1 # reset $end
$var wire 8 & wdata [7:0] $end
$var wire 1 % wr $end
$var reg 8 ' data [7:0] $end
$upscope $end
$upscope $end
$enddefinitions $end
#0
$dumpvars
bx '
b0 &
0%
b0 $
0#
0"
bx !
$end
#5
1"
#10
0"
#15
1"
#20
0"
#25
1"
#30
0"
#35
1"
#40
0"
#45
1"
#50
b0 !
b0 '
0"
1#
#54
0#
#55
b1 !
b1 '
1"
#60
0"
#65
b10 !
b10 '
1"
#70
0"
#75
b11 !
b11 '
1"
#80
0"
#85
b100 !
b100 '
1"
#90
0"
#95
b101 !
b101 '
1"
#100
0"
#105
b110 !
b110 '
1%
b1010101 $
b1010101 &
1"
#110
0"
#115
b1010101 !
b1010101 '
0%
b0 $
b0 &
1"
#120
0"
#125
b1010110 !
b1010110 '
1"
#130
0"
#135
b1010111 !
b1010111 '
1"
#140
0"
#145
b1011000 !
b1011000 '
1"
#150
0"
#155
b1011001 !
b1011001 '
1"
#160
0"
#165
b1011010 !
b1011010 '
1"
#170
0"
#175
b1011011 !
b1011011 '
1"
#180
0"
#185
b1011100 !
b1011100 '
1"
#190
0"
#195
b1011101 !
b1011101 '
1"
#200
0"
#205
b1011110 !
b1011110 '
1"
#210
0"
#215
b1011111 !
b1011111 '
1"
#220
0"
#225
b1100000 !
b1100000 '
1"
#230
0"
#235
b1100001 !
b1100001 '
1"
#240
0"
#245
b1100010 !
b1100010 '
1"
#250
0"
#255
b1100011 !
b1100011 '
1"
#260
0"
#265
b1100100 !
b1100100 '
1"
#270
0"
#275
b1100101 !
b1100101 '
1"
#280
0"
#285
b1100110 !
b1100110 '
1"
#290
0"
#295
b1100111 !
b1100111 '
1"
#300
0"
#305
b1101000 !
b1101000 '
1"
#310
0"
#315
b1101001 !
b1101001 '
1"
#320
0"
#325
b1101010 !
b1101010 '
1"
#330
0"
#335
b1101011 !
b1101011 '
1"
#340
0"
#345
b1101100 !
b1101100 '
1"
#350
0"
#355
b1101101 !
b1101101 '
1"
#360
0"
#365
b1101110 !
b1101110 '
1"
#370
0"
#375
b1101111 !
b1101111 '
1"
#380
0"
#385
b1110000 !
b1110000 '
1"
#390
0"
#395
b1110001 !
b1110001 '
1"
#400
0"
#405
b1110010 !
b1110010 '
1"
#410
0"
#415
b1110011 !
b1110011 '
1"
#420
0"
#425
b1110100 !
b1110100 '
1"
#430
0"
#435
b1110101 !
b1110101 '
1"
#440
0"
#445
b1110110 !
b1110110 '
1"
#450
0"
#455
b1110111 !
b1110111 '
1"
#460
0"
#465
b1111000 !
b1111000 '
1"
#470
0"
#475
b1111001 !
b1111001 '
1"
#480
0"
#485
b1111010 !
b1111010 '
1"
#490
0"
#495
b1111011 !
b1111011 '
1"
#500
0"
#505
b1111100 !
b1111100 '
1"
#510
0"
#515
b1111101 !
b1111101 '
1"
#520
0"
#525
b1111110 !
b1111110 '
1"
#530
0"
#535
b1111111 !
b1111111 '
1"
#540
0"
#545
b10000000 !
b10000000 '
1"
#550
0"
#555
b10000001 !
b10000001 '
1"
#560
0"
#565
b10000010 !
b10000010 '
1"
#570
0"
#575
b10000011 !
b10000011 '
1"
#580
0"
#585
b10000100 !
b10000100 '
1"
#590
0"
#595
b10000101 !
b10000101 '
1"
#600
0"
#605
b10000110 !
b10000110 '
1"
#610
0"
#615
b10000111 !
b10000111 '
1"
#620
0"
#625
b10001000 !
b10001000 '
1"
#630
0"
#635
b10001001 !
b10001001 '
1"
#640
0"
#645
b10001010 !
b10001010 '
1"
#650
0"
#655
b10001011 !
b10001011 '
1"
#660
0"
#665
b10001100 !
b10001100 '
1"
#670
0"
#675
b10001101 !
b10001101 '
1"
#680
0"
#685
b10001110 !
b10001110 '
1"
#690
0"
#695
b10001111 !
b10001111 '
1"
#700
0"
#705
b10010000 !
b10010000 '
1"
#710
0"
#715
b10010001 !
b10010001 '
1"
#720
0"
#725
b10010010 !
b10010010 '
1"
#730
0"
#735
b10010011 !
b10010011 '
1"
#740
0"
#745
b10010100 !
b10010100 '
1"
#750
0"
#755
b10010101 !
b10010101 '
1"
#760
0"
#765
b10010110 !
b10010110 '
1"
#770
0"
#775
b10010111 !
b10010111 '
1"
#780
0"
#785
b10011000 !
b10011000 '
1"
#790
0"
#795
b10011001 !
b10011001 '
1"
#800
0"
#805
b10011010 !
b10011010 '
1"
